{"name":"build-javascript","namedChunkGroups":{"polyfill":{"name":"polyfill","assets":[{"name":"webpack-runtime-5bcb98391d9b2f87af06.js","size":5240},{"name":"polyfill-ef19463019048f287105.js","size":85826}],"filteredAssets":0,"assetsSize":91066,"filteredAuxiliaryAssets":2,"auxiliaryAssetsSize":228178},"app":{"name":"app","assets":[{"name":"webpack-runtime-5bcb98391d9b2f87af06.js","size":5240},{"name":"framework-df4383517e8296105cfa.js","size":149073},{"name":"app-fff9a4adbc0656552287.js","size":56147}],"filteredAssets":0,"assetsSize":210460,"filteredAuxiliaryAssets":3,"auxiliaryAssetsSize":610131},"component---src-pages-404-js":{"name":"component---src-pages-404-js","assets":[{"name":"styles.235a417f77c8be0d42a0.css","size":2847},{"name":"commons-f32e7f05a720f1a63c06.js","size":16659},{"name":"component---src-pages-404-js-3a5521ada6cfcbfdaa52.js","size":443}],"filteredAssets":0,"assetsSize":19949,"filteredAuxiliaryAssets":2,"auxiliaryAssetsSize":70985},"component---src-pages-index-js":{"name":"component---src-pages-index-js","assets":[{"name":"styles.235a417f77c8be0d42a0.css","size":2847},{"name":"545f34e4-f22902edc14a6c6bc9ce.js","size":1014},{"name":"d7eeaac4-0599074c1d1f95ed4725.js","size":979},{"name":"commons-f32e7f05a720f1a63c06.js","size":16659},{"name":"component---src-pages-index-js-999dffe7c3613f38879b.js","size":21746}],"filteredAssets":0,"assetsSize":43245,"filteredAuxiliaryAssets":4,"auxiliaryAssetsSize":8047144},"component---src-templates-recipe-template-js":{"name":"component---src-templates-recipe-template-js","assets":[{"name":"styles.235a417f77c8be0d42a0.css","size":2847},{"name":"0c428ae2-82cb6fee7d168e9d0afd.js","size":2096},{"name":"commons-f32e7f05a720f1a63c06.js","size":16659},{"name":"component---src-templates-recipe-template-js-50721b4c238d5d4dbaee.js","size":4393}],"filteredAssets":0,"assetsSize":25995,"filteredAuxiliaryAssets":3,"auxiliaryAssetsSize":603745},"component---src-templates-small-recipes-template-js":{"name":"component---src-templates-small-recipes-template-js","assets":[{"name":"styles.235a417f77c8be0d42a0.css","size":2847},{"name":"0c428ae2-82cb6fee7d168e9d0afd.js","size":2096},{"name":"commons-f32e7f05a720f1a63c06.js","size":16659},{"name":"component---src-templates-small-recipes-template-js-599ccf41364331dee876.js","size":4261}],"filteredAssets":0,"assetsSize":25863,"filteredAuxiliaryAssets":3,"auxiliaryAssetsSize":603059}},"assetsByChunkName":{"polyfill":["webpack-runtime-5bcb98391d9b2f87af06.js","polyfill-ef19463019048f287105.js"],"app":["webpack-runtime-5bcb98391d9b2f87af06.js","framework-df4383517e8296105cfa.js","app-fff9a4adbc0656552287.js"],"component---src-pages-404-js":["styles.235a417f77c8be0d42a0.css","commons-f32e7f05a720f1a63c06.js","component---src-pages-404-js-3a5521ada6cfcbfdaa52.js"],"component---src-pages-index-js":["styles.235a417f77c8be0d42a0.css","545f34e4-f22902edc14a6c6bc9ce.js","d7eeaac4-0599074c1d1f95ed4725.js","commons-f32e7f05a720f1a63c06.js","component---src-pages-index-js-999dffe7c3613f38879b.js"],"component---src-templates-recipe-template-js":["styles.235a417f77c8be0d42a0.css","0c428ae2-82cb6fee7d168e9d0afd.js","commons-f32e7f05a720f1a63c06.js","component---src-templates-recipe-template-js-50721b4c238d5d4dbaee.js"],"component---src-templates-small-recipes-template-js":["styles.235a417f77c8be0d42a0.css","0c428ae2-82cb6fee7d168e9d0afd.js","commons-f32e7f05a720f1a63c06.js","component---src-templates-small-recipes-template-js-599ccf41364331dee876.js"]},"childAssetsByChunkName":{}}